duckiter/__init__.py
duckiter/config.py
duckiter/duckiter.py
duckiter/main.py
duckiter/utility.py
duckiter/validation.py
duckiter/template/__init__.py
duckiter/template/config_cfg.py
duckiter/template/docker_file.py
duckiter-0.1.9.dist-info/LICENSE
duckiter-0.1.9.dist-info/METADATA
duckiter-0.1.9.dist-info/WHEEL
duckiter-0.1.9.dist-info/entry_points.txt
duckiter-0.1.9.dist-info/top_level.txt
duckiter-0.1.9.dist-info/RECORD
