Metadata-Version: 2.1
Name: duckiter
Version: 0.1.9
Summary: Dockerize your django project
Home-page: https://github.com/coci/duckiter
Author: Soroush Safari
Author-email: mr.safarii1992@gmail.com
License: GPLv3
Platform: UNKNOWN
Classifier: Operating System :: OS Independent
Classifier: License :: OSI Approved :: GNU General Public License v3 (GPLv3)
Classifier: Programming Language :: Python :: 3.6
Classifier: Programming Language :: Python :: 3.7
Classifier: Programming Language :: Python :: 3.8
Classifier: Programming Language :: Python :: 3.9
Requires-Python: >=3.6
Requires-Dist: docker (==4.4.1)
Requires-Dist: six (==1.15.0)
Requires-Dist: websocket-client (==0.57.0)
Requires-Dist: wheel (==0.36.2)
Requires-Dist: rich (==9.10.0)
Requires-Dist: Jinja2 (==2.11.1)
